{
  "cate": "6",
  "date": "10æ19æ¥ 23æ55å",
  "datetime": "2017-10-19T23:55",
  "video": "https://www3.nhk.or.jp/news/html/20171019/movie/k10011183441_201710201207_201710201239.html",
  "duration": 86,
  "img": "html/20171019/K10011183441_1710200019_1710200020_01_02.jpg",
  "title": "100歳の仏の女優ダニエル・ダリューさん死去",
  "summary": "第１次世界大戦中の１９１７年に生まれ、８０年余りにわたって活躍し、ことし１００歳を迎えたフランスの女優、ダニエル・ダリューさんが１７日、亡くなりました。",
  "more": "ダニエル・ダリューさんは第１次世界大戦中の１９１７年、フランス南西部のボルドーに生まれ、１４歳で映画デビューしました。美しい容姿と華麗な演技で一躍有名になりましたが、第２次世界大戦中はフランスがドイツの占領下に置かれる中、ドイツ人と芸術活動を続けたことで、厳しい批判を受けました。<br /><br />１９５４年にはフランスの作家スタンダールの小説を映画化した「赤と黒」に出演し、夫がいながら別の青年と恋に落ちる女性を演じ、大きな反響を呼びました。<br />また２００２年に公開された「８人の女たち」では邸宅で殺害された大富豪の男性の義理の母親役を８０代半ばで演じ、犯人捜しの過程で次々に秘密が暴かれる男性の妻や娘役を演じた年下のベテラン女優たちをしのぐ熱演が日本でも話題になりました。<br /><br />ダリューさんは最近まで仕事に熱意を持ち続け、ことし５月に１００歳を迎えましたが、複数のフランスメディアによりますと１７日、パリ近郊の自宅で亡くなったということです。<br /><br />フランスのニッサン文化相はツイッターで「彼女の才能や寛大さはフランス映画をより輝かしいものにした」とコメントし、長年の功績をたたえています。",
  "body": [
    {
      "title": "",
      "img": "",
      "align": "",
      "text": "",
      "textPos": ""
    }
  ],
  "relationNews": [],
  "relationLink": [],
  "word": [
    {
      "link": "word/0000005.html",
      "title": "おくやみ"
    }
  ],
  "news_id": "k10011183441000",
  "url": "http://www3.nhk.or.jp/news/html/20171019/k10011183441000.html"
}